aiotieba/logging.py
aiotieba/exception.py
aiotieba/enums.py
aiotieba/config.py
aiotieba/client.py
aiotieba/__init__.py
aiotieba/__version__.py
aiotieba/typing.py
aiotieba/const.py
aiotieba/core/blcp.py
aiotieba/core/net.py
aiotieba/core/__init__.py
aiotieba/core/http.py
aiotieba/core/account.py
aiotieba/core/websocket.py
aiotieba/api/__init__.py
aiotieba/api/top/_api.py
aiotieba/api/top/__init__.py
aiotieba/api/get_dislike_forums/_api.py
aiotieba/api/get_dislike_forums/__init__.py
aiotieba/api/get_dislike_forums/_classdef.py
aiotieba/api/get_dislike_forums/protobuf/GetDislikeListReqIdl_pb2.py
aiotieba/api/get_dislike_forums/protobuf/GetDislikeListResIdl_pb2.py
aiotieba/api/del_threads/_api.py
aiotieba/api/del_threads/__init__.py
aiotieba/api/del_thread/_api.py
aiotieba/api/del_thread/__init__.py
aiotieba/api/move/_api.py
aiotieba/api/move/__init__.py
aiotieba/api/get_bawu_perm/_api.py
aiotieba/api/get_bawu_perm/__init__.py
aiotieba/api/get_bawu_perm/_classdef.py
aiotieba/api/get_threads/_api.py
aiotieba/api/get_threads/__init__.py
aiotieba/api/get_threads/_classdef.py
aiotieba/api/get_threads/protobuf/FrsPageReqIdl_pb2.py
aiotieba/api/get_threads/protobuf/FrsPageResIdl_pb2.py
aiotieba/api/get_fid/_api.py
aiotieba/api/get_fid/__init__.py
aiotieba/api/get_images/_api.py
aiotieba/api/get_images/__init__.py
aiotieba/api/get_images/_classdef.py
aiotieba/api/get_roomlist_by_fid/_api.py
aiotieba/api/get_roomlist_by_fid/__init__.py
aiotieba/api/get_roomlist_by_fid/_classdef.py
aiotieba/api/get_follow_forums/_api.py
aiotieba/api/get_follow_forums/__init__.py
aiotieba/api/get_follow_forums/_classdef.py
aiotieba/api/handle_unblock_appeals/_api.py
aiotieba/api/handle_unblock_appeals/__init__.py
aiotieba/api/get_forum_level/_api.py
aiotieba/api/get_forum_level/__init__.py
aiotieba/api/get_forum_level/_classdef.py
aiotieba/api/get_forum_level/protobuf/GetLevelInfoResIdl_pb2.py
aiotieba-4.6.1.dist-info/RECORD
aiotieba-4.6.1.dist-info/WHEEL
aiotieba-4.6.1.dist-info/METADATA
aiotieba-4.6.1.dist-info/licenses/LICENSE
