Metadata-Version: 2.2
Name: aiotieba
Version: 4.6.1
Summary: Asynchronous I/O Client for Baidu Tieba
Keywords: baidu,tieba
Author-Email: lumina37 <starry.qvq@gmail.com>
Classifier: Development Status :: 4 - Beta
Classifier: Framework :: AsyncIO
Classifier: Intended Audience :: Developers
Classifier: License :: OSI Approved :: The Unlicense (Unlicense)
Classifier: Operating System :: OS Independent
Classifier: Programming Language :: Python :: 3.9
Classifier: Programming Language :: Python :: 3.10
Classifier: Programming Language :: Python :: 3.11
Classifier: Programming Language :: Python :: 3.12
Classifier: Programming Language :: Python :: 3.13
Classifier: Programming Language :: Python :: 3.14
Classifier: Topic :: Internet :: WWW/HTTP :: Session
Project-URL: Repository, https://github.com/lumina37/aiotieba/
Project-URL: Documentation, https://aiotieba.cc/
Requires-Python: <3.15,>=3.9
Requires-Dist: aiohttp<4,>=3.11.0; python_version >= "3.9" and python_version < "3.12"
Requires-Dist: aiohttp<4,>=3.11.0; python_version == "3.12"
Requires-Dist: aiohttp<4,>=3.11.0; python_version == "3.13"
Requires-Dist: aiohttp<4,>=3.13.0; python_version >= "3.14"
Requires-Dist: beautifulsoup4<5,>=4.5.2; python_version == "3.9"
Requires-Dist: beautifulsoup4<5,>=4.7.1; python_version >= "3.10"
Requires-Dist: lxml<7,>=4.6.0; python_version == "3.9"
Requires-Dist: lxml<7,>=4.6.4; python_version == "3.10"
Requires-Dist: lxml<7,>=4.9.2; python_version == "3.11"
Requires-Dist: lxml<7,>=4.9.3; python_version == "3.12"
Requires-Dist: lxml<7,>=5.3.0; python_version == "3.13"
Requires-Dist: lxml<7,>=6.0.1; python_version >= "3.14"
Requires-Dist: protobuf<7,>=4.21.1
Requires-Dist: cryptography<41,>=35.0.0; python_version >= "3.9" and python_version < "3.12"
Requires-Dist: cryptography<47,>=35.0.0; python_version >= "3.12"
Requires-Dist: async-timeout<6,>=4.0; python_version < "3.11"
Requires-Dist: StrEnum<0.5,>=0.4.0; python_version < "3.11"
Provides-Extra: img
Requires-Dist: opencv-contrib-python-headless<5,>=4.6.0.66; sys_platform == "linux" and extra == "img"
Requires-Dist: opencv-contrib-python<5,>=4.6.0.66; sys_platform != "linux" and extra == "img"
Provides-Extra: speedup
Requires-Dist: orjson<4,>=2.2.0; python_version == "3.9" and extra == "speedup"
Requires-Dist: orjson<4,>=3.4.7; python_version == "3.10" and extra == "speedup"
Requires-Dist: orjson<4,>=3.7.10; python_version == "3.11" and extra == "speedup"
Requires-Dist: orjson<4,>=3.9.10; python_version == "3.12" and extra == "speedup"
Requires-Dist: orjson<4,>=3.10.7; python_version == "3.13" and extra == "speedup"
Requires-Dist: orjson<4,>=3.11.1; python_version >= "3.14" and extra == "speedup"
Requires-Dist: uvloop<1.0,>=0.15.0; python_version == "3.9" and sys_platform != "win32" and extra == "speedup"
Requires-Dist: uvloop<1.0,>=0.16.0; python_version == "3.10" and sys_platform != "win32" and extra == "speedup"
Requires-Dist: uvloop<1.0,>=0.17.0; python_version == "3.11" and sys_platform != "win32" and extra == "speedup"
Requires-Dist: uvloop<1.0,>=0.18.0; python_version == "3.12" and sys_platform != "win32" and extra == "speedup"
Requires-Dist: uvloop<1.0,>=0.21.0; python_version >= "3.13" and sys_platform != "win32" and extra == "speedup"
